ibis_analytics/__init__.py
ibis_analytics/catalog.py
ibis_analytics/cli.py
ibis_analytics/config.py
ibis_analytics/metrics.py
ibis_analytics/plots.py
ibis_analytics/tables.py
ibis_analytics/etl/__init__.py
ibis_analytics/etl/extract.py
ibis_analytics/etl/run.py
ibis_analytics/etl/transform.py
ibis_analytics/ingest/__init__.py
ibis_analytics/ingest/graphql_queries.py
ibis_analytics/ingest/run.py
ibis_analytics-0.12.0.dist-info/METADATA
ibis_analytics-0.12.0.dist-info/WHEEL
ibis_analytics-0.12.0.dist-info/entry_points.txt
ibis_analytics-0.12.0.dist-info/licenses/LICENSE
ibis_analytics-0.12.0.dist-info/RECORD
